hnefatafl/__init__.py
hnefatafl/game.py
hnefatafl/main.py
hnefatafl/utils.py
pyhnefatafl-0.3.2.dist-info/LICENSE
pyhnefatafl-0.3.2.dist-info/METADATA
pyhnefatafl-0.3.2.dist-info/WHEEL
pyhnefatafl-0.3.2.dist-info/RECORD
