Metadata-Version: 2.1
Name: pyhnefatafl
Version: 0.3.2
Summary: Hnefatafl (11x11) game engine for Python
Home-page: https://github.com/SootyOwl/pyhnefatafl
License: GPL-3.0-or-later
Author: SootyOwl
Author-email: tyto@tyto.cc
Requires-Python: >=3.8,<3.12
Classifier: License :: OSI Approved :: GNU General Public License v3 or later (GPLv3+)
Classifier: Programming Language :: Python :: 3
Classifier: Programming Language :: Python :: 3.8
Classifier: Programming Language :: Python :: 3.9
Classifier: Programming Language :: Python :: 3.10
Classifier: Programming Language :: Python :: 3.11
Classifier: Topic :: Games/Entertainment :: Board Games
Requires-Dist: numpy (>=1.24.1,<2.0.0)
Project-URL: Repository, https://github.com/SootyOwl/pyhnefatafl
